import_graph_python/__init__.py
import_graph_python/__main__.py
import_graph_python/cli.py
import_graph_python-0.1.0.dist-info/LICENSE
import_graph_python-0.1.0.dist-info/METADATA
import_graph_python-0.1.0.dist-info/WHEEL
import_graph_python-0.1.0.dist-info/entry_points.txt
import_graph_python-0.1.0.dist-info/top_level.txt
import_graph_python-0.1.0.dist-info/RECORD
